apiclient_pydantic_generator/__init__.py
apiclient_pydantic_generator/__main__.py
apiclient_pydantic_generator/format.py
apiclient_pydantic_generator/parser.py
apiclient_pydantic_generator/templates/__init__.jinja2
apiclient_pydantic_generator/templates/client.jinja2
apiclient_pydantic_generator/templates/endpoints.jinja2
apiclient_pydantic_generator-0.1.0.dist-info/entry_points.txt
apiclient_pydantic_generator-0.1.0.dist-info/LICENSE
apiclient_pydantic_generator-0.1.0.dist-info/WHEEL
apiclient_pydantic_generator-0.1.0.dist-info/METADATA
apiclient_pydantic_generator-0.1.0.dist-info/RECORD
