Metadata-Version: 2.1
Name: apiclient-pydantic-generator
Version: 0.1.0
Summary: This code generator creates a ApiClient app from an openapi file.
Home-page: https://github.com/mom1/apiclient-pydantic-generator
License: MIT
Author: MaxST
Author-email: mstolpasov@gmail.com
Requires-Python: >=3.7,<4.0
Classifier: Development Status :: 4 - Beta
Classifier: Environment :: Console
Classifier: License :: OSI Approved :: MIT License
Classifier: Programming Language :: Python :: 3
Classifier: Programming Language :: Python :: 3.10
Classifier: Programming Language :: Python :: 3.7
Classifier: Programming Language :: Python :: 3.8
Classifier: Programming Language :: Python :: 3.9
Classifier: Programming Language :: Python :: Implementation :: CPython
Classifier: Topic :: Software Development :: Code Generators
Requires-Dist: Jinja2 (>=2.11.2,<4.0.0)
Requires-Dist: api-client (>=1.3,<2.0)
Requires-Dist: api-client-pydantic (>=1.1,<2.0)
Requires-Dist: datamodel-code-generator (>=0.11,<0.12)
Requires-Dist: isort (>=5.9,<6.0)
Requires-Dist: pydantic (>=1.5,<2.0)
Requires-Dist: stringcase (>=1.2,<2.0)
Requires-Dist: typer[all] (>=0.2.1,<0.5.0)
Requires-Dist: yapf (>=0.31,<0.32)
Project-URL: Repository, https://github.com/mom1/apiclient-pydantic-generator
